fractuversalis.py
fractuversalis-0.1.0a5.dist-info/WHEEL
fractuversalis-0.1.0a5.dist-info/METADATA
fractuversalis-0.1.0a5.dist-info/RECORD
