Metadata-Version: 2.1
Name: fractuversalis
Version: 0.1.0a5
Summary: Shattered world mod generator for EU4
Author-email: Belreau Cohen <nuu.chah.nulth@disroot.org>
Requires-Python: >=3.7,<4
Classifier: License :: OSI Approved :: MIT License
Requires-Dist: sortedcontainers >=2,<3
Project-URL: Home, https://github.com/Belstowe/fractuversalis.git
